airflow/providers/amazon/__init__.py
airflow/providers/amazon/aws/__init__.py
airflow/providers/amazon/aws/example_dags/__init__.py
airflow/providers/amazon/aws/example_dags/example_datasync_1.py
airflow/providers/amazon/aws/example_dags/example_datasync_2.py
airflow/providers/amazon/aws/example_dags/example_ecs_fargate.py
airflow/providers/amazon/aws/example_dags/example_emr_job_flow_automatic_steps.py
airflow/providers/amazon/aws/example_dags/example_emr_job_flow_manual_steps.py
airflow/providers/amazon/aws/example_dags/example_glacier_to_gcs.py
airflow/providers/amazon/aws/example_dags/example_google_api_to_s3_transfer_advanced.py
airflow/providers/amazon/aws/example_dags/example_google_api_to_s3_transfer_basic.py
airflow/providers/amazon/aws/example_dags/example_imap_attachment_to_s3.py
airflow/providers/amazon/aws/example_dags/example_s3_bucket.py
airflow/providers/amazon/aws/example_dags/example_s3_to_redshift.py
airflow/providers/amazon/aws/hooks/__init__.py
airflow/providers/amazon/aws/hooks/athena.py
airflow/providers/amazon/aws/hooks/aws_dynamodb.py
airflow/providers/amazon/aws/hooks/base_aws.py
airflow/providers/amazon/aws/hooks/batch_client.py
airflow/providers/amazon/aws/hooks/batch_waiters.json
airflow/providers/amazon/aws/hooks/batch_waiters.py
airflow/providers/amazon/aws/hooks/cloud_formation.py
airflow/providers/amazon/aws/hooks/datasync.py
airflow/providers/amazon/aws/hooks/dynamodb.py
airflow/providers/amazon/aws/hooks/ec2.py
airflow/providers/amazon/aws/hooks/elasticache_replication_group.py
airflow/providers/amazon/aws/hooks/emr.py
airflow/providers/amazon/aws/hooks/glacier.py
airflow/providers/amazon/aws/hooks/glue.py
airflow/providers/amazon/aws/hooks/glue_catalog.py
airflow/providers/amazon/aws/hooks/glue_crawler.py
airflow/providers/amazon/aws/hooks/kinesis.py
airflow/providers/amazon/aws/hooks/lambda_function.py
airflow/providers/amazon/aws/hooks/logs.py
airflow/providers/amazon/aws/hooks/redshift.py
apache_airflow_backport_providers_amazon-2021.3.3.dist-info/LICENSE
apache_airflow_backport_providers_amazon-2021.3.3.dist-info/METADATA
apache_airflow_backport_providers_amazon-2021.3.3.dist-info/NOTICE
apache_airflow_backport_providers_amazon-2021.3.3.dist-info/WHEEL
apache_airflow_backport_providers_amazon-2021.3.3.dist-info/top_level.txt
apache_airflow_backport_providers_amazon-2021.3.3.dist-info/RECORD
