Metadata-Version: 2.1
Name: apache-airflow-backport-providers-amazon
Version: 2021.3.3
Summary: Backport provider package apache-airflow-backport-providers-amazon for Apache Airflow
Home-page: https://airflow.apache.org/
Author: Apache Software Foundation
Author-email: dev@airflow.apache.org
License: Apache License 2.0
Download-URL: https://archive.apache.org/dist/airflow/backport-providers
Project-URL: Documentation, https://airflow.apache.org/docs/
Project-URL: Bug Tracker, https://github.com/apache/airflow/issues
Project-URL: Source Code, https://github.com/apache/airflow
Platform: UNKNOWN
Classifier: Development Status :: 5 - Production/Stable
Classifier: Environment :: Console
Classifier: Environment :: Web Environment
Classifier: Intended Audience :: Developers
Classifier: Intended Audience :: System Administrators
Classifier: License :: OSI Approved :: Apache Software License
Classifier: Programming Language :: Python :: 3.6
Classifier: Programming Language :: Python :: 3.7
Classifier: Programming Language :: Python :: 3.8
Classifier: Topic :: System :: Monitoring
Requires-Python: ~=3.6
Requires-Dist: apache-airflow (~=1.10)
Requires-Dist: boto3 (<1.16.0,>=1.15.0)
Requires-Dist: botocore (<1.19.0,>=1.18.0)
Requires-Dist: watchtower (~=0.7.3)
Provides-Extra: apache.hive
Requires-Dist: apache-airflow-backport-providers-apache-hive ; extra == 'apache.hive'
Provides-Extra: exasol
Requires-Dist: apache-airflow-backport-providers-exasol ; extra == 'exasol'
Provides-Extra: ftp
Requires-Dist: apache-airflow-backport-providers-ftp ; extra == 'ftp'
Provides-Extra: google
Requires-Dist: apache-airflow-backport-providers-google ; extra == 'google'
Provides-Extra: imap
Requires-Dist: apache-airflow-backport-providers-imap ; extra == 'imap'
Provides-Extra: mongo
Requires-Dist: apache-airflow-backport-providers-mongo ; extra == 'mongo'
Provides-Extra: mysql
Requires-Dist: apache-airflow-backport-providers-mysql ; extra == 'mysql'
Provides-Extra: postgres
Requires-Dist: apache-airflow-backport-providers-postgres ; extra == 'postgres'
Provides-Extra: ssh
Requires-Dist: apache-airflow-backport-providers-ssh ; extra == 'ssh'
